{
  "version": "1.12.0",
  "compound": {
    "kind": "class",
    "id": "class_atlas_scientific_d_o___d_omg_l",
    "name": "AtlasScientificDO_DOmgL",
    "url_base": "class_atlas_scientific_d_o___d_omg_l",
    "url": "class_atlas_scientific_d_o___d_omg_l.html",
    "include": [
      "&lt;src/sensors/AtlasScientificDO.h&gt;",
      "_atlas_scientific_d_o_8h.html"
    ],
    "has_template_details": false,
    "templates": null,
    "brief": "The <a href=\"class_variable.html\" class=\"m-doc\">Variable</a> sub-class used for the <a href=\"group__sensor__atlas__do.html#sensor_atlas_do_concentration\" class=\"m-doc\">dissolved oxygen concentration output</a> from an <a href=\"group__sensor__atlas__do.html\" class=\"m-doc\">Atlas Scientific EZO dissolved oxygen circuit</a>.",
    "description": "",
    "sections": "",
    "deprecated": null,
    "since": null,
    "example_navigation": null,
    "footer_navigation": null,
    "topics": [],
    "dirs": [],
    "files": [],
    "namespaces": [],
    "classes": [],
    "base_classes": [
      {
        "kind": "class",
        "url": "class_variable.html",
        "name": "Variable",
        "brief": "The variable class for a value and related metadata.",
        "templates": null,
        "deprecated": null,
        "since": null,
        "is_protected": false,
        "is_virtual": false
      }
    ],
    "derived_classes": [],
    "enums": [],
    "typedefs": [],
    "funcs": [],
    "vars": [],
    "defines": [],
    "public_types": [],
    "public_static_funcs": [],
    "typeless_funcs": [
      {
        "base_url": "class_atlas_scientific_d_o___d_omg_l.html",
        "id": "a86c13715afe434456306f9df24fbe07f",
        "include": null,
        "has_details": true,
        "type": "",
        "name": "AtlasScientificDO_DOmgL",
        "brief": "Construct a new <a href=\"class_atlas_scientific_d_o___d_omg_l.html\" class=\"m-doc\">AtlasScientificDO_<wbr />DOmgL</a> object.",
        "description": "",
        "return_value": null,
        "return_values": [],
        "exceptions": [],
        "deprecated": null,
        "since": null,
        "is_constexpr": false,
        "is_consteval": false,
        "is_explicit": true,
        "is_virtual": false,
        "prefix": "",
        "is_defaulted": false,
        "is_deleted": false,
        "is_pure_virtual": false,
        "is_final": false,
        "is_override": false,
        "is_noexcept": false,
        "is_conditional_noexcept": false,
        "suffix": "",
        "is_protected": false,
        "is_private": false,
        "is_signal": false,
        "is_slot": false,
        "has_template_details": false,
        "templates": null,
        "has_param_details": true,
        "params": [
          {
            "name": "parentSense",
            "type": "<a href=\"class_atlas_scientific_d_o.html\" class=\"m-doc\">AtlasScientificDO</a>*",
            "type_name": "<a href=\"class_atlas_scientific_d_o.html\" class=\"m-doc\">AtlasScientificDO</a>* parentSense",
            "default": null,
            "description": "The parent <a href=\"class_atlas_scientific_d_o.html\" class=\"m-doc\">AtlasScientificDO</a> providing the result values.",
            "direction": ""
          },
          {
            "name": "uuid",
            "type": "const char*",
            "type_name": "const char* uuid",
            "default": "&quot;&quot;",
            "description": "A universally unique identifier (UUID or GUID) for the variable; optional with the default value of an empty string.",
            "direction": ""
          },
          {
            "name": "varCode",
            "type": "const char*",
            "type_name": "const char* varCode",
            "default": "&quot;AtlasDOmgL&quot;",
            "description": "A short code to help identify the variable in files; optional with a default value of &quot;AtlasDOmgL&quot;.",
            "direction": ""
          }
        ]
      },
      {
        "base_url": "class_atlas_scientific_d_o___d_omg_l.html",
        "id": "a478140a694b416972e177ad5ef2d815d",
        "include": null,
        "has_details": true,
        "type": "",
        "name": "AtlasScientificDO_DOmgL",
        "brief": "Construct a new <a href=\"class_atlas_scientific_d_o___d_omg_l.html\" class=\"m-doc\">AtlasScientificDO_<wbr />DOmgL</a> object.",
        "description": "<aside class=\"m-note m-info\"><h4>Note</h4><p>This must be tied with a parent <a href=\"class_atlas_scientific_d_o.html\" class=\"m-doc\">AtlasScientificDO</a> before it can be used.</p></aside>",
        "return_value": null,
        "return_values": [],
        "exceptions": [],
        "deprecated": null,
        "since": null,
        "is_constexpr": false,
        "is_consteval": false,
        "is_explicit": false,
        "is_virtual": false,
        "prefix": "",
        "is_defaulted": false,
        "is_deleted": false,
        "is_pure_virtual": false,
        "is_final": false,
        "is_override": false,
        "is_noexcept": false,
        "is_conditional_noexcept": false,
        "suffix": "",
        "is_protected": false,
        "is_private": false,
        "is_signal": false,
        "is_slot": false,
        "has_template_details": false,
        "templates": null,
        "has_param_details": false,
        "params": []
      },
      {
        "base_url": "class_atlas_scientific_d_o___d_omg_l.html",
        "id": "a615c72a08da6b3c33349d4f462d29655",
        "include": null,
        "has_details": false,
        "type": "",
        "name": "~AtlasScientificDO_DOmgL",
        "brief": "Destroy the <a href=\"class_atlas_scientific_d_o___d_omg_l.html\" class=\"m-doc\">AtlasScientificDO_<wbr />DOmgL</a> object - no action needed.",
        "description": "",
        "return_value": null,
        "return_values": [],
        "exceptions": [],
        "deprecated": null,
        "since": null,
        "is_constexpr": false,
        "is_consteval": false,
        "is_explicit": false,
        "is_virtual": false,
        "prefix": "",
        "is_defaulted": false,
        "is_deleted": false,
        "is_pure_virtual": false,
        "is_final": false,
        "is_override": false,
        "is_noexcept": false,
        "is_conditional_noexcept": false,
        "suffix": "",
        "is_protected": false,
        "is_private": false,
        "is_signal": false,
        "is_slot": false,
        "has_template_details": false,
        "templates": null,
        "has_param_details": false,
        "params": []
      }
    ],
    "public_funcs": [],
    "signals": [],
    "public_slots": [],
    "public_static_vars": [],
    "public_vars": [],
    "protected_types": [],
    "protected_static_funcs": [],
    "protected_funcs": [],
    "protected_slots": [],
    "protected_static_vars": [],
    "protected_vars": [],
    "private_funcs": [],
    "private_slots": [],
    "related": [],
    "friend_funcs": [],
    "groups": [],
    "has_enum_details": false,
    "has_typedef_details": false,
    "has_func_details": true,
    "has_var_details": false,
    "has_define_details": false,
    "breadcrumb": [
      [
        "Variable",
        "class_variable.html"
      ],
      [
        "AtlasScientificDO_DOmgL",
        "class_atlas_scientific_d_o___d_omg_l.html"
      ]
    ],
    "breadcrumbGroup": [
      [
        "Atlas EZO-DO",
        "group__sensor__atlas__do.html"
      ],
      [
        "AtlasScientificDO_DOmgL",
        "class_atlas_scientific_d_o___d_omg_l.html"
      ]
    ],
    "is_final": false,
    "prefix_wbr": "AtlasScientificDO_<wbr />DOmgL::<wbr />"
  }
}